examples/__init__.py
examples/app.py
examples/config.py
examples/validators.py
examples/middlewares/__init__.py
examples/middlewares/authed.py
examples/models/__init__.py
examples/models/accounts.py
examples/models/billers.py
examples/models/cards.py
examples/models/files.py
examples/models/transactions.py
examples/models/users.py
examples/resources/__init__.py
examples/resources/accounts.py
examples/resources/base.py
examples/resources/billers.py
examples/resources/cards.py
examples/resources/files.py
examples/resources/transactions.py
examples/resources/users.py
examples/tasks/__init__.py
examples/tasks/retry_task_example.py
examples/tasks/task_example.py
fast_agave/__init__.py
fast_agave/exc.py
fast_agave/filters.py
fast_agave/version.py
fast_agave/blueprints/__init__.py
fast_agave/blueprints/decorators.py
fast_agave/blueprints/rest_api.py
fast_agave/middlewares/__init__.py
fast_agave/middlewares/error_handlers.py
fast_agave/tasks/__init__.py
fast_agave/tasks/sqs_celery_client.py
fast_agave/tasks/sqs_client.py
fast_agave/tasks/sqs_tasks.py
tests/__init__.py
tests/conftest.py
tests/test_app.py
tests/blueprint/__init__.py
tests/blueprint/test_blueprint.py
tests/blueprint/test_decorators.py
tests/tasks/__init__.py
tests/tasks/test_sqs_celery_client.py
tests/tasks/test_sqs_client.py
tests/tasks/test_sqs_tasks.py
fast_agave-0.14.1.dist-info/LICENSE
fast_agave-0.14.1.dist-info/METADATA
fast_agave-0.14.1.dist-info/WHEEL
fast_agave-0.14.1.dist-info/top_level.txt
fast_agave-0.14.1.dist-info/RECORD
