Metadata-Version: 2.1
Name: fast_agave
Version: 0.14.1
Summary: Rest api blueprints for fast-api
Home-page: https://github.com/cuenca-mx/fast-agave
Author: Cuenca
Author-email: dev@cuenca.com
Classifier: Programming Language :: Python :: 3.8
Classifier: License :: OSI Approved :: MIT License
Classifier: Operating System :: OS Independent
Requires-Python: >=3.8
License-File: LICENSE
Requires-Dist: aiobotocore <3.0.0,>=1.0.0
Requires-Dist: types-aiobotocore-sqs <3.0.0,>=2.1.0.post1
Requires-Dist: cuenca-validations <1.0.0,>=0.9.4
Requires-Dist: fastapi <0.69.0,>=0.63.0
Requires-Dist: mongoengine-plus <1.0.0,>=0.0.2
Requires-Dist: starlette-context <0.4.0,>=0.3.2
